sage/middleware/py.typed
sage/middleware/enterprise/sage_db/tests/test_python.py
sage/middleware/enterprise/sage_db/tests/__pycache__/test_python.cpython-311.opt-2.pyc
sage/middleware/enterprise/sage_db/tests/__pycache__/test_python.cpython-311.pyc
intellistream_sage_middleware-0.1.3.dist-info/METADATA
intellistream_sage_middleware-0.1.3.dist-info/WHEEL
intellistream_sage_middleware-0.1.3.dist-info/top_level.txt
intellistream_sage_middleware-0.1.3.dist-info/RECORD
